servants/__init__.py
servants/test_tool_example.py
servants-0.2.1.dist-info/METADATA
servants-0.2.1.dist-info/WHEEL
servants-0.2.1.dist-info/top_level.txt
servants-0.2.1.dist-info/RECORD
