Metadata-Version: 2.4
Name: servants
Version: 0.2.1
Summary: A simple library for prototyping and learning agent-based reasoning with tools.
Author: rabeeqiblawi
Author-email: rabeeqiblawi <rabeeqiblawi@gmail.com>
License-Expression: MIT
Requires-Python: >=3.7
Dynamic: author
